gia_shell_genie/__init__.py
gia_shell_genie/aliases.yml
gia_shell_genie/backends.py
gia_shell_genie/main.py
gia_shell_genie/utils.py
gia_shell_genie-0.2.15.dist-info/LICENSE
gia_shell_genie-0.2.15.dist-info/METADATA
gia_shell_genie-0.2.15.dist-info/WHEEL
gia_shell_genie-0.2.15.dist-info/entry_points.txt
gia_shell_genie-0.2.15.dist-info/RECORD
