Metadata-Version: 2.1
Name: gia-shell-genie
Version: 0.2.15
Summary: (GIA distribution of )Shell Genie is a command-line tool that lets you interact with the terminal in plain English. You ask the genie what you want to do and it will give you the command you need.
License: MIT
Author: jgwill
Author-email: jgwill@gmail.com
Requires-Python: >=3.10,<4.0
Classifier: License :: OSI Approved :: MIT License
Classifier: Programming Language :: Python :: 3
Classifier: Programming Language :: Python :: 3.10
Classifier: Programming Language :: Python :: 3.11
Classifier: Programming Language :: Python :: 3.12
Requires-Dist: openai (>=0.26.0,<1.0.0)
Requires-Dist: pyperclip (>=1.8.2,<2.0.0)
Requires-Dist: typer[all] (>=0.7.0,<0.8.0)
